{"tw_pre": {"updated_at": "2026-06-23T15:31:48.701482", "headline": {"text": "昨夜美股平穩 → 台股開盤中性，看個股表現", "color": "#888"}, "sections": [{"title": "🌃 昨夜美股", "open": true, "html": "<table><thead><tr><th>指數</th><th>漲跌</th><th>點數</th></tr></thead><tbody><tr><td>道瓊</td><td><span style='color:#16a34a;font-weight:700'>▲0.29%</span></td><td>51,713</td></tr><tr><td>S&P 500</td><td><span style='color:#dc2626;font-weight:700'>▼0.37%</span></td><td>7,473</td></tr><tr><td>Nasdaq</td><td><span style='color:#dc2626;font-weight:700'>▼1.32%</span></td><td>26,167</td></tr><tr><td>費城半導體</td><td><span style='color:#16a34a;font-weight:700'>▲2.04%</span></td><td>14,635</td></tr></tbody></table>"}, {"title": "🔗 ADR 開盤暗示", "open": true, "html": "<table><thead><tr><th>ADR</th><th>隔夜</th><th>暗示</th></tr></thead><tbody><tr><td>台積電ADR→2330</td><td><span style='color:#16a34a;font-weight:700'>▲1.15%</span></td><td>有撐</td></tr><tr><td>聯電ADR→2303</td><td><span style='color:#16a34a;font-weight:700'>▲13.73%</span></td><td>有撐</td></tr></tbody></table><p style='font-size:11px;color:#888;margin-top:4px'>ADR 是台積電/聯電的美國存託憑證，昨夜漲跌常領先台股開盤</p>"}, {"title": "🏦 昨日三大法人（06/23）", "open": false, "html": "<table><thead><tr><th>法人</th><th>買賣超</th></tr></thead><tbody><tr><td>外資</td><td>-386 億</td></tr><tr><td>投信</td><td>+72 億</td></tr><tr><td>自營</td><td>-170 億</td></tr><tr><td>合計</td><td>-484 億</td></tr></tbody></table>"}, {"title": "📅 重要事件（總經 + 財報）", "open": true, "html": "<div style='font-size:12px;margin:4px 0'>📊 最新數據：CPI 年增率 <b>+4.2%</b>（2026/05）｜PPI 最終需求年增率 <b>+6.5%</b>（2026/05）</div><b style='font-size:13px'>📅 持股/清單即將財報（7日內）</b><table><thead><tr><th>股票</th><th>公布日</th><th>倒數</th></tr></thead><tbody><tr><td>⚠️ 美光（MU）</td><td>2026-06-24</td><td>1天後</td></tr></tbody></table>"}, {"title": "📰 隔夜新聞", "open": false, "html": "<ul><li>➡️ 熱門股／外資目標價上看1444元！南電一度勁揚逾9% 欣興、景碩走跌| 產經 - 非凡新聞台 <span style='color:#999;font-size:11px'>06-23</span></li><li>📈 載板三雄唯獨它最亮眼！南電無懼大盤強勢領漲 聚焦三大利多 - UDN <span style='color:#999;font-size:11px'>06-23</span></li><li>📈 美股收盤／那斯達克跌逾1% Alphabet領大型科技股下挫但費半續創新高| 全球財經| 全球  <span style='color:#999;font-size:11px'>06-22</span></li><li>➡️ 美股收盤》SpaceX暴跌16.4％！ 台積電與聯電ADR皆收紅 - 自由財經 <span style='color:#999;font-size:11px'>06-22</span></li></ul>"}]}, "tw_post": {"updated_at": "2026-06-23T15:31:53.889961", "headline": {"text": "加權收 47,101（-1.43%）", "color": "#dc2626"}, "sections": [{"title": "📊 大盤收盤", "open": true, "html": "<table><thead><tr><th>指數</th><th>收盤</th><th>漲跌</th></tr></thead><tbody><tr><td>加權指數</td><td>47,101</td><td><span style='color:#dc2626;font-weight:700'>▼1.43%</span></td></tr></tbody></table>"}, {"title": "🏦 今日三大法人（06/23）", "open": true, "html": "<table><thead><tr><th>法人</th><th>買賣超</th></tr></thead><tbody><tr><td>外資</td><td>-386 億</td></tr><tr><td>投信</td><td>+72 億</td></tr><tr><td>自營</td><td>-170 億</td></tr><tr><td>合計</td><td>-484 億</td></tr></tbody></table>"}, {"title": "🔄 板塊資金流向", "open": false, "html": "<div style='font-size:13px'>🔥 流入：FOCUS_AI伺服器(+31.5%)、AI伺服器(+31.5%)、FOCUS_晶圓代工(+8.5%)<br>❄️ 流出：低軌衛星(-2.5%)、FOCUS_低軌衛星(-2.5%)、金融保險(-1.9%)</div>"}]}, "us_pre": {"updated_at": "2026-06-23T15:31:56.823157", "headline": {"text": "Nasdaq 期貨 -1.16% → 今晚美股開盤偏弱", "color": "#dc2626"}, "sections": [{"title": "📈 美股期貨（開盤前指標）", "open": true, "html": "<table><thead><tr><th>期貨</th><th>現值</th><th>漲跌</th></tr></thead><tbody><tr><td>S&P 期貨</td><td>7,449</td><td><span style='color:#dc2626;font-weight:700'>▼0.76%</span></td></tr><tr><td>Nasdaq 期貨</td><td>30,032</td><td><span style='color:#dc2626;font-weight:700'>▼1.16%</span></td></tr><tr><td>道瓊 期貨</td><td>51,788</td><td><span style='color:#dc2626;font-weight:700'>▼0.58%</span></td></tr></tbody></table>"}, {"title": "😱 風險指標", "open": true, "html": "<table><thead><tr><th>指標</th><th>現值</th><th>漲跌</th></tr></thead><tbody><tr><td>VIX 恐慌</td><td>19.74</td><td><span style='color:#16a34a;font-weight:700'>▲14.24%</span></td></tr><tr><td>10年期殖利率</td><td>4.51</td><td><span style='color:#16a34a;font-weight:700'>▲1.30%</span></td></tr></tbody></table>"}, {"title": "🔗 台股收盤暗示", "open": false, "html": "<div style='font-size:13px'>台股加權收 47,101（<span style='color:#dc2626;font-weight:700'>▼1.43%</span>）→ 台股弱，美科技股留意</div>"}, {"title": "📅 重要事件（總經 + 財報）", "open": true, "html": "<div style='font-size:12px;margin:4px 0'>📊 最新數據：CPI 年增率 <b>+4.2%</b>（2026/05）｜PPI 最終需求年增率 <b>+6.5%</b>（2026/05）</div><b style='font-size:13px'>📅 持股/清單即將財報（7日內）</b><table><thead><tr><th>股票</th><th>公布日</th><th>倒數</th></tr></thead><tbody><tr><td>⚠️ 美光（MU）</td><td>2026-06-24</td><td>1天後</td></tr></tbody></table>"}]}, "us_post": {"updated_at": "2026-06-23T15:32:00.277420", "headline": {"text": "隔夜美股：收黑", "color": "#f59e0b"}, "sections": [{"title": "📊 三大指數 + 費半 + VIX + 殖利率", "open": true, "html": "<table><thead><tr><th>指標</th><th>漲跌</th><th>數值</th></tr></thead><tbody><tr><td>S&P 500</td><td><span style='color:#dc2626;font-weight:700'>▼0.37%</span></td><td>7,472.79</td></tr><tr><td>Nasdaq</td><td><span style='color:#dc2626;font-weight:700'>▼1.32%</span></td><td>26,166.60</td></tr><tr><td>道瓊</td><td><span style='color:#16a34a;font-weight:700'>▲0.29%</span></td><td>51,712.71</td></tr><tr><td>費城半導體</td><td><span style='color:#16a34a;font-weight:700'>▲2.04%</span></td><td>14,634.72</td></tr><tr><td>VIX 恐慌指數</td><td><span style='color:#16a34a;font-weight:700'>▲14.24%</span></td><td>19.74</td></tr><tr><td>10年期美債殖利率</td><td><span style='color:#dc2626;font-weight:700'>▼0.27%</span></td><td>4.45</td></tr></tbody></table>"}, {"title": "🔍 漲跌歸因", "open": true, "html": "<ul><li>🔻 Nasdaq 弱於 S&P → 賣壓集中在科技/成長股</li></ul>"}, {"title": "📰 新聞佐證", "open": false, "html": "<ul><li>Fed 4月、6月聲明比一比：華許掌舵後內容大瘦身 抗通膨立場更鮮明 - news.cnyes.com</li><li>聯準會換將通膨高漲 美股面臨升息修正壓力 - Yahoo股市</li></ul>"}]}, "analysis_hero": {"updated_at": "2026-06-23T15:32:04.052888", "twii": {"name": "加權指數", "sym": "^TWII", "last": 47100.65, "chg": -1.43}, "sox": {"name": "費城半導體", "sym": "^SOX", "last": 14634.72, "chg": 2.04}, "nasdaq": {"name": "Nasdaq", "sym": "^IXIC", "last": 26166.6, "chg": -1.32}, "nq_fut": {"name": "Nasdaq期貨", "sym": "NQ=F", "last": 30031.75, "chg": -1.16}, "advance_decline": {"up": 236, "down": 757, "flat": 70, "date": "06/23"}, "institutional": {"自營": -169.8, "投信": 72.2, "外資": -385.9, "合計": -483.6, "date": "06/23"}}, "market_health": {"updated_at": "2026-06-23T15:32:04.052888", "index": {"last": 47100.65, "chg": -1.34}, "ma": {"20": {"val": 45070.0, "above": true}, "60": {"val": 40458.0, "above": true}, "120": {"val": 36161.0, "above": true}, "240": {"val": 30861.0, "above": true}}, "ma_above": 4, "alignment": ["多頭排列", "#dc2626"], "rsi": 56.5, "macd": {"hist": 87.1, "state": "紅柱轉強", "bull": true}, "volume": {"ratio": 0.97, "state": "量平"}, "advance_decline": {"up": 236, "down": 757, "flat": 70, "date": "06/23"}, "valuation": {"pe": 21.2, "yield": 3.24, "pb": 1.8, "n": 1078, "pe_label": "合理"}, "margin": {"date": "06/22", "short_bal": 202267, "short_chg": -2090, "margin_amt": 6050.0, "margin_chg": 120.0}, "foreign_futures": {"date": "2026-06-23", "long_oi": 10506, "short_oi": 87008, "net_oi": -76502, "stance": "偏空", "source": "finmind"}, "usdtwd": {"last": 31.644, "chg": -0.18, "chg20": 0.62, "ma20": 31.541, "twd_strong": false, "state": "台幣偏貶(外資偏匯出)"}, "credit": {"ratio": 0.7349, "chg20": -0.38, "risk_on": true, "state": "風險偏好升(信用買帳)", "divergence": false}, "health_score": 6, "health": ["強健多頭", "#dc2626"]}}