{
  "scan_time": "2026-07-17T22:00:30.628246",
  "benchmark": {
    "sym": "SPY",
    "chg": -0.8,
    "r20": 0.77
  },
  "sectors": [
    {
      "sym": "XLV",
      "name": "醫療",
      "rs": 7.92,
      "consecutive": 24,
      "flow_dir": "in",
      "last": 163.08,
      "chg": 0.79,
      "r5": 1.39,
      "r20": 8.69,
      "above_ma20": true,
      "above_ma50": true,
      "vol_ratio": 0.16
    },
    {
      "sym": "XLE",
      "name": "能源",
      "rs": 5.87,
      "consecutive": 1,
      "flow_dir": "in",
      "last": 57.88,
      "chg": 1.52,
      "r5": 5.09,
      "r20": 6.64,
      "above_ma20": true,
      "above_ma50": true,
      "vol_ratio": 0.23
    },
    {
      "sym": "XLF",
      "name": "金融",
      "rs": 4.65,
      "consecutive": 24,
      "flow_dir": "in",
      "last": 56.78,
      "chg": 0.05,
      "r5": 1.92,
      "r20": 5.42,
      "above_ma20": true,
      "above_ma50": true,
      "vol_ratio": 0.19
    },
    {
      "sym": "XLRE",
      "name": "房地產",
      "rs": 4.35,
      "consecutive": 1,
      "flow_dir": "in",
      "last": 45.82,
      "chg": 0.79,
      "r5": 3.08,
      "r20": 5.12,
      "above_ma20": true,
      "above_ma50": true,
      "vol_ratio": 0.13
    },
    {
      "sym": "XLP",
      "name": "必需消費",
      "rs": 3.92,
      "consecutive": 1,
      "flow_dir": "in",
      "last": 87.0,
      "chg": 1.39,
      "r5": 3.42,
      "r20": 4.69,
      "above_ma20": true,
      "above_ma50": true,
      "vol_ratio": 0.24
    },
    {
      "sym": "XLU",
      "name": "公用",
      "rs": 3.31,
      "consecutive": 2,
      "flow_dir": "in",
      "last": 45.98,
      "chg": 1.12,
      "r5": 1.26,
      "r20": 4.08,
      "above_ma20": true,
      "above_ma50": true,
      "vol_ratio": 0.14
    },
    {
      "sym": "IGV",
      "name": "軟體",
      "rs": 3.22,
      "consecutive": 2,
      "flow_dir": "in",
      "last": 92.72,
      "chg": -1.05,
      "r5": 0.34,
      "r20": 3.99,
      "above_ma20": true,
      "above_ma50": false,
      "vol_ratio": 0.12
    },
    {
      "sym": "XLC",
      "name": "通訊服務",
      "rs": 1.29,
      "consecutive": 1,
      "flow_dir": "in",
      "last": 111.16,
      "chg": -1.32,
      "r5": -0.43,
      "r20": 2.06,
      "above_ma20": true,
      "above_ma50": false,
      "vol_ratio": 0.11
    },
    {
      "sym": "XLY",
      "name": "非必需消費",
      "rs": 0.48,
      "consecutive": 0,
      "flow_dir": "neutral",
      "last": 116.7,
      "chg": -0.55,
      "r5": -0.46,
      "r20": 1.25,
      "above_ma20": true,
      "above_ma50": false,
      "vol_ratio": 0.13
    },
    {
      "sym": "XLI",
      "name": "工業",
      "rs": -0.07,
      "consecutive": 0,
      "flow_dir": "neutral",
      "last": 180.41,
      "chg": 0.14,
      "r5": -0.83,
      "r20": 0.7,
      "above_ma20": false,
      "above_ma50": true,
      "vol_ratio": 0.14
    },
    {
      "sym": "XLB",
      "name": "原物料",
      "rs": -2.21,
      "consecutive": 6,
      "flow_dir": "out",
      "last": 51.08,
      "chg": 0.37,
      "r5": 0.37,
      "r20": -1.44,
      "above_ma20": false,
      "above_ma50": true,
      "vol_ratio": 0.12
    },
    {
      "sym": "XLK",
      "name": "科技",
      "rs": -7.11,
      "consecutive": 2,
      "flow_dir": "out",
      "last": 173.81,
      "chg": -2.09,
      "r5": -6.44,
      "r20": -6.34,
      "above_ma20": false,
      "above_ma50": false,
      "vol_ratio": 0.22
    },
    {
      "sym": "SMH",
      "name": "半導體",
      "rs": -12.67,
      "consecutive": 2,
      "flow_dir": "out",
      "last": 549.73,
      "chg": -3.37,
      "r5": -10.03,
      "r20": -11.9,
      "above_ma20": false,
      "above_ma50": false,
      "vol_ratio": 0.41
    }
  ],
  "summary": "資金輪入：醫療、能源、金融　｜　輪出：原物料、科技、半導體",
  "note": "RS=該板塊ETF 20日報酬 − SPY 20日報酬（>0=強於大盤＝資金輪入）。資料源 yfinance ETF。"
}